setup.py
runbds/__init__.py
runbds/bodies.py
runbds/body.py
runbds/helper.py
runbds/run.py
runbds.egg-info/PKG-INFO
runbds.egg-info/SOURCES.txt
runbds.egg-info/dependency_links.txt
runbds.egg-info/top_level.txt