Metadata-Version: 2.1
Name: runbds
Version: 1.3.0
Summary: run the bodies
Author: Riming Desmond
Author-email: dhjfirst@hotmail.com
License: apache 3.0
Requires: numpy
